ankipan/__init__.py
ankipan/anki_manager.py
ankipan/card.py
ankipan/client.py
ankipan/collection.py
ankipan/config.py
ankipan/deck.py
ankipan/gpt_base.py
ankipan/reader.py
ankipan/util.py
ankipan-0.6.dist-info/licenses/LICENSE
ankipan-0.6.dist-info/METADATA
ankipan-0.6.dist-info/WHEEL
ankipan-0.6.dist-info/top_level.txt
ankipan-0.6.dist-info/RECORD
