Metadata-Version: 2.4
Name: ankipan
Version: 0.6
Summary: A language learning utility with Anki integration
Author-email: Daniel Otto de Mentock <daniel.mentock@gmail.com>
License: AGPL-3.0
Project-URL: repository, https://gitlab.com/ankipan/ankipan
Classifier: Intended Audience :: Education
Classifier: Topic :: Education
Classifier: Operating System :: OS Independent
Classifier: Programming Language :: Python
Classifier: Programming Language :: Python :: 3
Classifier: Programming Language :: Python :: 3.10
Classifier: Programming Language :: Python :: 3.11
Classifier: Programming Language :: Python :: 3.12
Classifier: Programming Language :: Python :: 3.13
Classifier: Programming Language :: Python :: 3 :: Only
Classifier: Typing :: Typed
Requires-Python: >=3.10
License-File: LICENSE
Requires-Dist: beautifulsoup4
Requires-Dist: chardet
Requires-Dist: PyMuPDF
Requires-Dist: Flask
Requires-Dist: Jinja2
Requires-Dist: langdetect
Requires-Dist: Markdown
Requires-Dist: numpy
Requires-Dist: protobuf
Requires-Dist: pykakasi
Requires-Dist: pysubs2
Requires-Dist: PyYAML
Requires-Dist: Requests
Requires-Dist: tqdm
Requires-Dist: wcwidth
Requires-Dist: pytest
Requires-Dist: google-generativeai
Requires-Dist: ipywidgets
Dynamic: license-file
